{"version":"https://jsonfeed.org/version/1","title":"blog // Drew Powers","items":[{"id":"http://localhost:3000/posts/the-state-of-es-modules-in-2020.html","url":"http://localhost:3000/posts/the-state-of-es-modules-in-2020.html","title":"the state of ES Modules in 2020","content_html":"The biggest change to JavaScript in years is a shockingly-quiet revolution","content_text":null,"date_published":"Sun, 08 Mar 2020 12:00:00 +0000","tags":[]},{"id":"http://localhost:3000/posts/3-pillars-of-front-end-knowledge.html","url":"http://localhost:3000/posts/3-pillars-of-front-end-knowledge.html","title":"the 3 pillars of front-end knowledge","content_html":"The world of front-end is vast, so where does one start? And where does mastery end?","content_text":null,"date_published":"Mon, 17 Feb 2020 12:00:00 +0000","tags":[]},{"id":"http://localhost:3000/posts/media-queries-are-still-a-hack.html","url":"http://localhost:3000/posts/media-queries-are-still-a-hack.html","title":"media queries are (still) a hack","content_html":"Revisiting Ian Storm Taylor’s thoughts 7 years later","content_text":null,"date_published":"Sat, 18 Jan 2020 12:00:00 +0000","tags":[]},{"id":"http://localhost:3000/posts/playfulness-budget.html","url":"http://localhost:3000/posts/playfulness-budget.html","title":"playfulness budget","content_html":"Finding that sweet spot of delight and whimsy in application design","content_text":null,"date_published":"Wed, 06 Nov 2019 12:00:00 +0000","tags":[]}],"home_page_url":"http://localhost:3000","description":"The personal blog of Drew Powers"}